dataverk_gsm/__init__.py
dataverk_gsm/api.py
dataverk_gsm-0.0.2.dist-info/LICENSE
dataverk_gsm-0.0.2.dist-info/METADATA
dataverk_gsm-0.0.2.dist-info/WHEEL
dataverk_gsm-0.0.2.dist-info/top_level.txt
dataverk_gsm-0.0.2.dist-info/RECORD
