Metadata-Version: 2.1
Name: dataverk-gsm
Version: 0.0.2
Summary: GSM integration for dataverk
Home-page: https://github.com/navikt
Author: NAV IKT
License: MIT
Keywords: gsm dataverk
Platform: UNKNOWN
Requires-Python: >=3.6
Requires-Dist: google-auth (>=1.24.0)
Requires-Dist: google-cloud-secret-manager (>=1.0.0)
Requires-Dist: google-cloud-core (>=1.4.3)
